Crypted/Algorand/__init__.py
Crypted/Algorand/__init__.pyi
Crypted/Algorand/config.py
Crypted/Algorand/errors.py
Crypted/Algorand/py.typed
Crypted/Algorand/stack_frame.py
Crypted/Algorand/stack_frame_test.py
Crypted/Algorand/types.py
Crypted/Algorand/types_test.py
Crypted/Algorand/util.py
Crypted/Algorand/ast/__init__.py
Crypted/Algorand/ast/abstractvar.py
Crypted/Algorand/ast/acct.py
Crypted/Algorand/ast/acct_test.py
Crypted/Algorand/ast/addr.py
Crypted/Algorand/ast/addr_test.py
Crypted/Algorand/ast/app.py
Crypted/Algorand/ast/app_test.py
Crypted/Algorand/ast/arg.py
Crypted/Algorand/ast/arg_test.py
Crypted/Algorand/ast/array.py
Crypted/Algorand/ast/assert_.py
Crypted/Algorand/ast/assert_test.py
Crypted/Algorand/ast/asset.py
Crypted/Algorand/ast/asset_test.py
Crypted/Algorand/ast/base64decode.py
Crypted/Algorand/ast/base64decode_test.py
Crypted/Algorand/ast/binaryexpr.py
Crypted/Algorand/ast/binaryexpr_test.py
Crypted/Algorand/ast/block.py
Crypted/Algorand/ast/block_test.py
Crypted/Algorand/ast/box.py
Crypted/Algorand/ast/box_test.py
Crypted/Algorand/ast/break_.py
Crypted/Algorand/ast/break_test.py
Crypted/Algorand/ast/bytes.py
Crypted/Algorand/ast/bytes_test.py
Crypted/Algorand/ast/comment.py
Crypted/Algorand/ast/comment_test.py
Crypted/Algorand/ast/cond.py
Crypted/Algorand/ast/cond_test.py
Crypted/Algorand/ast/continue_.py
Crypted/Algorand/ast/continue_test.py
Crypted/Algorand/ast/ec.py
Crypted/Algorand/ast/ec_test.py
Crypted/Algorand/ast/ecdsa.py
Crypted/Algorand/ast/ecdsa_test.py
Crypted/Algorand/ast/err.py
Crypted/Algorand/ast/err_test.py
Crypted/Algorand/ast/expr.py
Crypted/Algorand/ast/for_.py
Crypted/Algorand/ast/for_test.py
Crypted/Algorand/ast/frame.py
Crypted/Algorand/ast/frame_test.py
Crypted/Algorand/ast/gaid.py
Crypted/Algorand/ast/gaid_test.py
Crypted/Algorand/ast/gitxn.py
Crypted/Algorand/ast/gitxn_test.py
Crypted/Algorand/ast/gload.py
Crypted/Algorand/ast/gload_test.py
Crypted/Algorand/ast/global_.py
Crypted/Algorand/ast/global_test.py
crypted-1.0.0.dist-info/METADATA
crypted-1.0.0.dist-info/WHEEL
crypted-1.0.0.dist-info/licenses/LICENCE
crypted-1.0.0.dist-info/RECORD
