Metadata-Version: 2.4
Name: Crypted
Version: 1.0.0
Summary: A Web3 Blockchain Library
Project-URL: Homepage, https://github.com/HampterPW/Crypted
Author-email: HampterPW <bradbeeschwarz@gmail.com>
License-Expression: MIT
License-File: LICENCE
Classifier: Operating System :: OS Independent
Classifier: Programming Language :: Python :: 3
Requires-Python: >=3.8
